cresbot/__init__.py
cresbot/cli/__init__.py
cresbot/cli/hiscore_counts.py
cresbot/cli/main.py
cresbot/mediawiki/__init__.py
cresbot/mediawiki/api.py
cresbot/rswiki/__init__.py
cresbot/rswiki/exchange.py
cresbot/rswiki/hiscore_counts_module.py
cresbot/runescape/__init__.py
cresbot/runescape/runedate.py
cresbot/runescape/exchange/__init__.py
cresbot/runescape/exchange/exchange_category.py
cresbot/runescape/exchange/exchange_database.py
cresbot/runescape/exchange/exchange_models.py
cresbot/runescape/exchange/exchange_page.py
cresbot/runescape/exchange/util.py
cresbot/runescape/hiscores/__init__.py
cresbot/runescape/hiscores/hiscores.py
tests/runescape/__init__.py
tests/runescape/test_runedate.py
cresbot-0.0.1.dist-info/METADATA
cresbot-0.0.1.dist-info/WHEEL
cresbot-0.0.1.dist-info/top_level.txt
cresbot-0.0.1.dist-info/RECORD
